{
	"name": "dataflow1",
	"properties": {
		"type": "MappingDataFlow",
		"typeProperties": {
			"sources": [
				{
					"dataset": {
						"referenceName": "AzureSqlTable5",
						"type": "DatasetReference"
					},
					"name": "source1"
				},
				{
					"dataset": {
						"referenceName": "AzureSqlTable6",
						"type": "DatasetReference"
					},
					"name": "source2"
				}
			],
			"sinks": [
				{
					"dataset": {
						"referenceName": "DelimitedText3",
						"type": "DatasetReference"
					},
					"name": "sink1"
				}
			],
			"transformations": [
				{
					"name": "join1"
				}
			],
			"scriptLines": [
				"source(output(",
				"          EmployeeID as integer,",
				"          EmployeeName as string,",
				"          DepartmentID as integer,",
				"          HireDate as date",
				"     ),",
				"     allowSchemaDrift: true,",
				"     validateSchema: false,",
				"     isolationLevel: 'READ_UNCOMMITTED',",
				"     format: 'table') ~> source1",
				"source(output(",
				"          DepartmentID as integer,",
				"          DepartmentName as string",
				"     ),",
				"     allowSchemaDrift: true,",
				"     validateSchema: false,",
				"     isolationLevel: 'READ_UNCOMMITTED',",
				"     format: 'table') ~> source2",
				"source1, source2 join(source1@DepartmentID == source2@DepartmentID,",
				"     joinType:'left',",
				"     matchType:'exact',",
				"     ignoreSpaces: false,",
				"     broadcast: 'auto')~> join1",
				"join1 sink(allowSchemaDrift: true,",
				"     validateSchema: false,",
				"     input(",
				"          CustomerID as string,",
				"          FirstName as string,",
				"          LastName as string,",
				"          Email as string,",
				"          City as string",
				"     ),",
				"     skipDuplicateMapInputs: true,",
				"     skipDuplicateMapOutputs: true) ~> sink1"
			]
		}
	}
}